ragsearch/__init__.py
ragsearch/config.py
ragsearch/engine.py
ragsearch/hello_world.py
ragsearch/setup.py
ragsearch/templates/index.html
ragsearch/utils.py
ragsearch/vector_db.py
ragsearch-0.1.3.dist-info/LICENSE
ragsearch-0.1.3.dist-info/METADATA
ragsearch-0.1.3.dist-info/WHEEL
ragsearch-0.1.3.dist-info/RECORD
