Metadata-Version: 2.3
Name: ragsearch
Version: 0.1.3
Summary: ragserach is a Python library designed for building a Retrieval-Augmented Generation (RAG) application that enables natural language querying over structured data. This tool leverages embedding models and a vector database (FAISS) to provide an efficient and scalable search engine.
License: MIT
Author: Mrutunjay Kinagi
Author-email:  mrutunjay.kinagi @ gmail.com 
Requires-Python: >=3.9,<4.0
Classifier: License :: OSI Approved :: MIT License
Classifier: Programming Language :: Python :: 3
Classifier: Programming Language :: Python :: 3.9
Classifier: Programming Language :: Python :: 3.10
Classifier: Programming Language :: Python :: 3.11
Classifier: Programming Language :: Python :: 3.12
Classifier: Programming Language :: Python :: 3.13
Requires-Dist: chromadb (>=1.0.20,<2.0.0)
Requires-Dist: cohere (>=5.17.0,<6.0.0)
Requires-Dist: faiss-cpu (>=1.12.0,<2.0.0) ; python_version >= "3.9" and python_version < "3.15"
Requires-Dist: fastavro (>=1.12.0,<2.0.0)
Requires-Dist: flask (>=3.1.2,<4.0.0)
Requires-Dist: pandas (>=2.2.3,<3.0.0)
Requires-Dist: pylint (>=3.3.1,<4.0.0)
Requires-Dist: pytest (>=8.3.3,<9.0.0)
Requires-Dist: sphinx (==7.4.7)
Requires-Dist: sphinx-rtd-theme (>=3.0.2,<4.0.0)
Project-URL: Repository, https://github.com/mrutunjay-kinagi/ragsearch
